io_bench/__init__.py
io_bench/io_bench.py
io_bench/utilities/__init__.py
io_bench/utilities/bench.py
io_bench/utilities/explain.py
io_bench/utilities/parsing.py
io_bench-0.1.0.dist-info/LICENSE.txt
io_bench-0.1.0.dist-info/METADATA
io_bench-0.1.0.dist-info/WHEEL
io_bench-0.1.0.dist-info/top_level.txt
io_bench-0.1.0.dist-info/RECORD
