Metadata-Version: 2.1
Name: io_bench
Version: 0.1.0
Summary: IO Bench is a library designed to benchmark the performance of standard flat file formats and partitioning schemes.
Author: Aaron Stopher
License: Copyright (c) 2018 The Python Packaging Authority
Project-URL: Homepage, https://github.com/aastopher/io_bench
Project-URL: Documentation, https://aastopher.github.io/io_bench/
Project-URL: Bug Reports, https://github.com/aastopher/io_bench/issues
Keywords: arrow,avro,feather,parquet,polars,utils,performance counter,benchmark
Classifier: Programming Language :: Python :: 3
Classifier: Programming Language :: Python :: 3.6
Classifier: Programming Language :: Python :: 3.7
Classifier: Programming Language :: Python :: 3.8
Classifier: Programming Language :: Python :: 3.9
Classifier: Programming Language :: Python :: 3.10
Classifier: Programming Language :: Python :: 3.11
Classifier: Programming Language :: Python :: 3.12
Classifier: License :: OSI Approved :: MIT License
Classifier: Operating System :: POSIX :: Linux
Requires-Python: >=3.6
License-File: LICENSE.txt
Requires-Dist: fastavro==1.9.5
Requires-Dist: fastparquet==2024.5.0
Requires-Dist: pandas==2.2.2
Requires-Dist: plotly==5.23.0
Requires-Dist: polars==1.4.0
Requires-Dist: psutil==6.0.0
Requires-Dist: pyarrow==17.0.0
Requires-Dist: rich==13.7.1
Provides-Extra: dev
Requires-Dist: virtualenv==20.26.3; extra == "dev"
Requires-Dist: mkdocs==1.6.0; extra == "dev"
Requires-Dist: mkdocstrings==0.25.2; extra == "dev"
Requires-Dist: mike==2.1.3; extra == "dev"
Provides-Extra: test
Requires-Dist: tox==4.16.0; extra == "test"
Requires-Dist: codecov==2.1.13; extra == "test"
Requires-Dist: pytest==8.3.2; extra == "test"
Requires-Dist: pytest-cov==5.0.0; extra == "test"
